django_postds/__init__.py
django_postds/admin.py
django_postds/apps.py
django_postds/forms.py
django_postds/models.py
django_postds/sitemaps.py
django_postds/tests.py
django_postds/urls.py
django_postds/views.py
django_postds/migrations/0001_initial.py
django_postds/migrations/__init__.py
django_postds/templatetags/django_postds_tags.py
django_postds-1.5.0.dist-info/LICENSE
django_postds-1.5.0.dist-info/WHEEL
django_postds-1.5.0.dist-info/METADATA
django_postds-1.5.0.dist-info/RECORD
