Metadata-Version: 2.1
Name: django_postds
Version: 1.5.0
Summary: my demiansoft post & portfolio parts
Author-email: Hyungjin Kim <hj3415@gmail.com>
Classifier: License :: OSI Approved :: MIT License
Requires-Dist: Django >= 4.2.11
Requires-Dist: libsass>=0.23.0
Requires-Dist: django-mdeditor >= 0.1.20
Requires-Dist: django-hitcount >= 1.3.5
Requires-Dist: django-taggit >= 5.0.1
Requires-Dist: django-light >= 0.1.0
Requires-Dist: pillow >= 10.3.0
Project-URL: Home, https://www.demiansoft.com
